mani_skill2/__init__.py
mani_skill2/agents/__init__.py
mani_skill2/agents/base_agent.py
mani_skill2/agents/base_controller.py
mani_skill2/agents/utils.py
mani_skill2/agents/configs/__init__.py
mani_skill2/agents/configs/mobile_panda/__init__.py
mani_skill2/agents/configs/mobile_panda/defaults.py
mani_skill2/agents/configs/panda/__init__.py
mani_skill2/agents/configs/panda/defaults.py
mani_skill2/agents/configs/panda/variants.py
mani_skill2/agents/configs/xmate3/__init__.py
mani_skill2/agents/configs/xmate3/defaults.py
mani_skill2/agents/controllers/__init__.py
mani_skill2/agents/controllers/passive_controller.py
mani_skill2/agents/controllers/pd_base_vel.py
mani_skill2/agents/controllers/pd_ee_pose.py
mani_skill2/agents/controllers/pd_joint_pos.py
mani_skill2/agents/controllers/pd_joint_pos_vel.py
mani_skill2/agents/controllers/pd_joint_vel.py
mani_skill2/agents/robots/__init__.py
mani_skill2/agents/robots/mobile_panda.py
mani_skill2/agents/robots/panda.py
mani_skill2/agents/robots/xmate3.py
mani_skill2/assets/maniskill2-scene-2.glb
mani_skill2/assets/deformable_manipulation/beaker.glb
mani_skill2/assets/deformable_manipulation/bottle.glb
mani_skill2/assets/descriptions/mobile_panda_dual_arm.urdf
mani_skill2/assets/descriptions/mobile_panda_single_arm.urdf
mani_skill2/assets/descriptions/panda_bucket.srdf
mani_skill2/assets/descriptions/panda_bucket.urdf
mani_skill2/assets/descriptions/panda_pinch.srdf
mani_skill2/assets/descriptions/panda_pinch.urdf
mani_skill2/assets/descriptions/panda_stick.srdf
mani_skill2/assets/descriptions/panda_stick.urdf
mani_skill2/assets/descriptions/panda_v2.srdf
mani_skill2/assets/descriptions/panda_v2.urdf
mani_skill2/assets/descriptions/panda_v2_gripper.urdf
mani_skill2/assets/descriptions/panda_v3.srdf
mani_skill2/assets/descriptions/panda_v3.urdf
mani_skill2/assets/descriptions/bucket/bucket.stl
mani_skill2/assets/descriptions/bucket/bucket_45.stl
mani_skill2/assets/descriptions/franka_description/meshes/collision/finger.stl
mani_skill2-0.5.3.dist-info/LICENSE
mani_skill2-0.5.3.dist-info/METADATA
mani_skill2-0.5.3.dist-info/WHEEL
mani_skill2-0.5.3.dist-info/top_level.txt
mani_skill2-0.5.3.dist-info/RECORD
