Metadata-Version: 2.1
Name: mani-skill2
Version: 0.5.3
Summary: ManiSkill2: A Unified Benchmark for Generalizable Manipulation Skills
Home-page: https://github.com/haosulab/ManiSkill2
Author: ManiSkill2 contributors
Requires-Python: >=3.8
License-File: LICENSE
Requires-Dist: numpy <1.24
Requires-Dist: scipy
Requires-Dist: gymnasium >=0.28.1
Requires-Dist: sapien ==2.2.2
Requires-Dist: h5py
Requires-Dist: pyyaml
Requires-Dist: tqdm
Requires-Dist: GitPython
Requires-Dist: tabulate
Requires-Dist: gdown >=4.6.0
Requires-Dist: transforms3d
Requires-Dist: opencv-python
Requires-Dist: imageio
Requires-Dist: imageio[ffmpeg]
Requires-Dist: trimesh
Requires-Dist: rtree
Provides-Extra: docs
Requires-Dist: sphinx ==6.2.1 ; extra == 'docs'
Requires-Dist: sphinx-autobuild ; extra == 'docs'
Requires-Dist: sphinx-rtd-theme ; extra == 'docs'
Requires-Dist: sphinxcontrib.spelling ; extra == 'docs'
Requires-Dist: sphinx-autodoc-typehints ; extra == 'docs'
Requires-Dist: sphinx-copybutton ; extra == 'docs'
Requires-Dist: myst-parser ; extra == 'docs'
Requires-Dist: sphinx-subfigure ; extra == 'docs'
Provides-Extra: tests
Requires-Dist: pytest ; extra == 'tests'
Requires-Dist: black ; extra == 'tests'
Requires-Dist: isort ; extra == 'tests'
